escpos_gen.py
escpos_gen-0.0.2.dist-info/LICENSE.txt
escpos_gen-0.0.2.dist-info/METADATA
escpos_gen-0.0.2.dist-info/WHEEL
escpos_gen-0.0.2.dist-info/top_level.txt
escpos_gen-0.0.2.dist-info/RECORD
