Metadata-Version: 2.1
Name: escpos_gen
Version: 0.0.2
Summary: Generator of printable binary files with helper methods based on ESC/POS protocol
Home-page: https://github.com/fercorbar/escpos_gen
Author: Fernando Córdova
Author-email: fernando@cbin.mx
License: UNKNOWN
Platform: UNKNOWN
Classifier: Programming Language :: Python :: 3
Classifier: Programming Language :: Python :: 3.6
Classifier: Programming Language :: Python :: 3.7
Classifier: License :: OSI Approved :: MIT License
Classifier: Operating System :: OS Independent
License-File: LICENSE.txt
